[
    {
        "client": "Amazon Books",
        "clientid": 95,
        "job": "Amazon job 123",
        "jobid": 94,
        "gps": [
            -104.323,
            45.573
        ],
        "time": 1516754771727,
        "deviceid": "c4:b3:01:d3:15:51",
        "mats": [
            {
                "id": "MA-0001-0002-0003",
                "gps": [
                    -104.323,
                    45.573
                ],
                "time": 1516754803873
            },
            {
                "id": "MA-0001-0002-0001",
                "gps": [
                    -104.323,
                    45.573
                ],
                "time": 1516754809881
            },
            {
                "id": "MA-MENG-0002-0001",
                "gps": [
                    -104.323,
                    45.573
                ],
                "time": 1516754805878
            },
            {
                "id": "MA-0001-0002-0004",
                "gps": [
                    -104.323,
                    45.573
                ],
                "time": 1516754785778
            },
            {
                "id": "MA-0001-0002-0002",
                "gps": [
                    -104.323,
                    45.573
                ],
                "time": 1516754815916
            },
            {
                "id": "MA-MENG-0002-0002",
                "gps": [
                    -104.323,
                    45.573
                ],
                "time": 1516754813914
            },
            {
                "id": "MA-MENG-0002-0003",
                "gps": [
                    -104.323,
                    45.573
                ],
                "time": 1516754791822
            },
            {
                "id": "MA-MENG-0002-0004",
                "gps": [
                    -104.323,
                    45.573
                ],
                "time": 1516754797838
            }
        ]
    }
]